LICENSE.txt
MANIFEST.in
README.rst
requirements.txt
setup.py
old_docs/__init__.py
old_docs/conf.py
tests/__init__.py
tests/test_basic.py
tests/utils.py
tests/core/__init__.py
tests/core/test_conf.py
wechat_sdk/__init__.py
wechat_sdk/base.py
wechat_sdk/basic.py
wechat_sdk/exceptions.py
wechat_sdk/ext.py
wechat_sdk/messages.py
wechat_sdk/reply.py
wechat_sdk/utils.py
wechat_sdk.egg-info/PKG-INFO
wechat_sdk.egg-info/SOURCES.txt
wechat_sdk.egg-info/dependency_links.txt
wechat_sdk.egg-info/requires.txt
wechat_sdk.egg-info/top_level.txt
wechat_sdk/context/__init__.py
wechat_sdk/context/framework/__init__.py
wechat_sdk/context/framework/django/__init__.py
wechat_sdk/context/framework/django/apps.py
wechat_sdk/context/framework/django/exceptions.py
wechat_sdk/context/framework/django/models.py
wechat_sdk/context/framework/django/serializers.py
wechat_sdk/context/framework/django/tests.py
wechat_sdk/context/framework/django/backends/__init__.py
wechat_sdk/context/framework/django/backends/base.py
wechat_sdk/context/framework/django/backends/db.py
wechat_sdk/context/framework/django/migrations/0001_initial.py
wechat_sdk/context/framework/django/migrations/__init__.py
wechat_sdk/core/__init__.py
wechat_sdk/core/conf.py
wechat_sdk/lib/__init__.py
wechat_sdk/lib/parser.py
wechat_sdk/lib/request.py
wechat_sdk/lib/crypto/__init__.py
wechat_sdk/lib/crypto/base.py
wechat_sdk/lib/crypto/crypto.py
wechat_sdk/lib/crypto/exceptions.py
wechat_sdk/lib/crypto/pkcs7.py
wechat_sdk/lib/crypto/utils.py