Metadata-Version: 1.0
Name: wechat-sdk
Version: 0.6.0
Summary: 微信公众平台Python开发包
Home-page: https://github.com/wechat-python-sdk/wechat-python-sdk
Author: doraemonext
Author-email: doraemonext@gmail.com
License: BSD License
Keywords: wechat,sdk,wechat sdk
Platform: UNKNOWN
